README.txt
setup.py
kidslearn/__init__.py
kidslearn/kids.py
kidslearn/opera.py
kidslearn.egg-info/PKG-INFO
kidslearn.egg-info/SOURCES.txt
kidslearn.egg-info/dependency_links.txt
kidslearn.egg-info/top_level.txt
kidslearn.egg-info/zip-safe