Metadata-Version: 1.1
Name: kidslearn
Version: 1.0.0
Summary: this is a kidslearn package for packing python liberaries tutorial.
Home-page: https://pypi.python.org/pypi/kidslearn/1.0.0
Author: zhangjunbiao
Author-email: zhangjunbiao2002@163.com
License: GPL3
Keywords: kids learn
Platform: UNKNOWN
Classifier: License :: OSI Approved :: MIT License
Classifier: Programming Language :: Python
Classifier: Intended Audience :: Developers
Classifier: Operating System :: OS Independent
